{"packages":{"yiisoft/yii2-bootstrap":{"2.0.10":{"name":"yiisoft/yii2-bootstrap","description":"The Twitter Bootstrap extension for the Yii framework","keywords":["bootstrap","yii2"],"homepage":"","version":"2.0.10","version_normalized":"2.0.10.0","license":["BSD-3-Clause"],"authors":[{"name":"Paul Klimov","email":"klimov.paul@gmail.com"},{"name":"Alexander Makarov","email":"sam@rmcreative.ru","homepage":"http://rmcreative.ru/"},{"name":"Antonio Ramirez","email":"amigo.cobos@gmail.com"},{"name":"Qiang Xue","email":"qiang.xue@gmail.com","homepage":"http://www.yiiframework.com/"}],"support":[],"dist":{"type":"zip","url":"https://api.github.com/repos/yiisoft/yii2-bootstrap/zipball/073c9ab0a4eb71f2485d84c96a1967130300d8fc","reference":"073c9ab0a4eb71f2485d84c96a1967130300d8fc","shasum":""},"type":"yii2-extension","time":"2019-04-23 13:18:43","autoload":{"psr-4":{"yii\\bootstrap\\":"src"}},"extra":{"branch-alias":{"dev-master":"2.0.x-dev"}},"require":{"yiisoft/yii2":"~2.0.6","bower-asset/bootstrap":"3.4.* | 3.3.* | 3.2.* | 3.1.*"},"uid":40672},"2.0.9":{"name":"yiisoft/yii2-bootstrap","description":"The Twitter Bootstrap extension for the Yii framework","keywords":["bootstrap","yii2"],"homepage":"","version":"2.0.9","version_normalized":"2.0.9.0","license":["BSD-3-Clause"],"authors":[{"name":"Paul Klimov","email":"klimov.paul@gmail.com"},{"name":"Alexander Makarov","email":"sam@rmcreative.ru","homepage":"http://rmcreative.ru/"},{"name":"Antonio Ramirez","email":"amigo.cobos@gmail.com"},{"name":"Qiang Xue","email":"qiang.xue@gmail.com","homepage":"http://www.yiiframework.com/"}],"support":[],"dist":{"type":"zip","url":"https://api.github.com/repos/yiisoft/yii2-bootstrap/zipball/4677951dda712dd99d5bf2a127eaee118dfea860","reference":"4677951dda712dd99d5bf2a127eaee118dfea860","shasum":""},"type":"yii2-extension","time":"2019-01-29 21:39:45","autoload":{"psr-4":{"yii\\bootstrap\\":"src"}},"extra":{"branch-alias":{"dev-master":"2.0.x-dev"}},"require":{"yiisoft/yii2":"~2.0.6","bower-asset/bootstrap":"3.4.* | 3.3.* | 3.2.* | 3.1.*"},"uid":38252},"2.0.8":{"name":"yiisoft/yii2-bootstrap","description":"The Twitter Bootstrap extension for the Yii framework","keywords":["bootstrap","yii2"],"homepage":"","version":"2.0.8","version_normalized":"2.0.8.0","license":["BSD-3-Clause"],"authors":[{"name":"Paul Klimov","email":"klimov.paul@gmail.com"},{"name":"Alexander Makarov","email":"sam@rmcreative.ru","homepage":"http://rmcreative.ru/"},{"name":"Antonio Ramirez","email":"amigo.cobos@gmail.com"},{"name":"Qiang Xue","email":"qiang.xue@gmail.com","homepage":"http://www.yiiframework.com/"}],"support":[],"dist":{"type":"zip","url":"https://api.github.com/repos/yiisoft/yii2-bootstrap/zipball/3f49c47924bb9fa5363c3fc7b073d954168cf438","reference":"3f49c47924bb9fa5363c3fc7b073d954168cf438","shasum":""},"type":"yii2-extension","time":"2018-02-16 10:41:52","autoload":{"psr-4":{"yii\\bootstrap\\":"src"}},"extra":{"branch-alias":{"dev-master":"2.0.x-dev"}},"require":{"yiisoft/yii2":"~2.0.6","bower-asset/bootstrap":"3.3.* | 3.2.* | 3.1.*"},"uid":14090},"2.0.7":{"name":"yiisoft/yii2-bootstrap","description":"The Twitter Bootstrap extension for the Yii framework","keywords":["bootstrap","yii2"],"homepage":"","version":"2.0.7","version_normalized":"2.0.7.0","license":["BSD-3-Clause"],"authors":[{"name":"Qiang Xue","email":"qiang.xue@gmail.com"}],"support":[],"dist":{"type":"zip","url":"https://api.github.com/repos/yiisoft/yii2-bootstrap/zipball/02a54d868343ed11d02f0f0f8cbbecb590e0cb3f","reference":"02a54d868343ed11d02f0f0f8cbbecb590e0cb3f","shasum":""},"type":"yii2-extension","time":"2017-10-09 19:48:22","autoload":{"psr-4":{"yii\\bootstrap\\":""}},"extra":{"branch-alias":{"dev-master":"2.0.x-dev"}},"require":{"yiisoft/yii2":"~2.0.6","bower-asset/bootstrap":"3.3.* | 3.2.* | 3.1.*"},"uid":4303},"2.0.3":{"name":"yiisoft/yii2-bootstrap","description":"The Twitter Bootstrap extension for the Yii framework","keywords":["bootstrap","yii2"],"homepage":"","version":"2.0.3","version_normalized":"2.0.3.0","license":["BSD-3-Clause"],"authors":[{"name":"Qiang Xue","email":"qiang.xue@gmail.com"}],"support":[],"dist":{"type":"zip","url":"https://api.github.com/repos/yiisoft/yii2-bootstrap/zipball/d4bd9c5f97ea891ebbfaf276d3083d85e27fbcb6","reference":"d4bd9c5f97ea891ebbfaf276d3083d85e27fbcb6","shasum":""},"type":"yii2-extension","time":"2015-03-01 06:22:44","autoload":{"psr-4":{"yii\\bootstrap\\":""}},"extra":{"branch-alias":{"dev-master":"2.0.x-dev"}},"require":{"yiisoft/yii2":"*","bower-asset/bootstrap":"3.3.* | 3.2.* | 3.1.*"},"uid":862},"2.0.6":{"name":"yiisoft/yii2-bootstrap","description":"The Twitter Bootstrap extension for the Yii framework","keywords":["bootstrap","yii2"],"homepage":"","version":"2.0.6","version_normalized":"2.0.6.0","license":["BSD-3-Clause"],"authors":[{"name":"Qiang Xue","email":"qiang.xue@gmail.com"}],"support":[],"dist":{"type":"zip","url":"https://api.github.com/repos/yiisoft/yii2-bootstrap/zipball/3fd2b8c950cce79d60e9702d6bcb24eb3c80f6c5","reference":"3fd2b8c950cce79d60e9702d6bcb24eb3c80f6c5","shasum":""},"type":"yii2-extension","time":"2016-03-17 03:29:28","autoload":{"psr-4":{"yii\\bootstrap\\":""}},"extra":{"branch-alias":{"dev-master":"2.0.x-dev"},"asset-installer-paths":{"npm-asset-library":"vendor/npm","bower-asset-library":"vendor/bower"}},"require":{"yiisoft/yii2":">=2.0.6","bower-asset/bootstrap":"3.3.* | 3.2.* | 3.1.*"},"uid":859},"2.0.5":{"name":"yiisoft/yii2-bootstrap","description":"The Twitter Bootstrap extension for the Yii framework","keywords":["bootstrap","yii2"],"homepage":"","version":"2.0.5","version_normalized":"2.0.5.0","license":["BSD-3-Clause"],"authors":[{"name":"Qiang Xue","email":"qiang.xue@gmail.com"}],"support":[],"dist":{"type":"zip","url":"https://api.github.com/repos/yiisoft/yii2-bootstrap/zipball/1464f93834b1d5edb1f5625f7ffd6c3723fa4923","reference":"1464f93834b1d5edb1f5625f7ffd6c3723fa4923","shasum":""},"type":"yii2-extension","time":"2015-09-23 17:48:24","autoload":{"psr-4":{"yii\\bootstrap\\":""}},"extra":{"branch-alias":{"dev-master":"2.0.x-dev"},"asset-installer-paths":{"npm-asset-library":"vendor/npm","bower-asset-library":"vendor/bower"}},"require":{"yiisoft/yii2":">=2.0.6","bower-asset/bootstrap":"3.3.* | 3.2.* | 3.1.*"},"uid":860},"2.0.4":{"name":"yiisoft/yii2-bootstrap","description":"The Twitter Bootstrap extension for the Yii framework","keywords":["bootstrap","yii2"],"homepage":"","version":"2.0.4","version_normalized":"2.0.4.0","license":["BSD-3-Clause"],"authors":[{"name":"Qiang Xue","email":"qiang.xue@gmail.com"}],"support":[],"dist":{"type":"zip","url":"https://api.github.com/repos/yiisoft/yii2-bootstrap/zipball/1b6b1e61cf91c3cdd517d6a7e71d30bb212e4af0","reference":"1b6b1e61cf91c3cdd517d6a7e71d30bb212e4af0","shasum":""},"type":"yii2-extension","time":"2015-05-10 22:08:17","autoload":{"psr-4":{"yii\\bootstrap\\":""}},"extra":{"branch-alias":{"dev-master":"2.0.x-dev"},"asset-installer-paths":{"npm-asset-library":"vendor/npm","bower-asset-library":"vendor/bower"}},"require":{"yiisoft/yii2":">=2.0.4","bower-asset/bootstrap":"3.3.* | 3.2.* | 3.1.*"},"uid":861},"2.0.2":{"name":"yiisoft/yii2-bootstrap","description":"The Twitter Bootstrap extension for the Yii framework","keywords":["bootstrap","yii2"],"homepage":"","version":"2.0.2","version_normalized":"2.0.2.0","license":["BSD-3-Clause"],"authors":[{"name":"Qiang Xue","email":"qiang.xue@gmail.com"}],"support":[],"dist":{"type":"zip","url":"https://api.github.com/repos/yiisoft/yii2-bootstrap/zipball/e3e4fdebb911ed64075adc0bab1b718531331138","reference":"e3e4fdebb911ed64075adc0bab1b718531331138","shasum":""},"type":"yii2-extension","time":"2015-01-11 03:57:55","autoload":{"psr-4":{"yii\\bootstrap\\":""}},"extra":{"branch-alias":{"dev-master":"2.0.x-dev"}},"require":{"yiisoft/yii2":"*","bower-asset/bootstrap":"3.3.* | 3.2.* | 3.1.*"},"uid":863},"2.0.1":{"name":"yiisoft/yii2-bootstrap","description":"The Twitter Bootstrap extension for the Yii framework","keywords":["bootstrap","yii2"],"homepage":"","version":"2.0.1","version_normalized":"2.0.1.0","license":["BSD-3-Clause"],"authors":[{"name":"Qiang Xue","email":"qiang.xue@gmail.com"}],"support":[],"dist":{"type":"zip","url":"https://api.github.com/repos/yiisoft/yii2-bootstrap/zipball/ca82a7a03ff5ed0d43294803edf1342de4efad17","reference":"ca82a7a03ff5ed0d43294803edf1342de4efad17","shasum":""},"type":"yii2-extension","time":"2014-12-07 16:42:41","autoload":{"psr-4":{"yii\\bootstrap\\":""}},"extra":{"branch-alias":{"dev-master":"2.0.x-dev"}},"require":{"yiisoft/yii2":"*","bower-asset/bootstrap":"3.3.* | 3.2.* | 3.1.*"},"uid":864},"2.0.0":{"name":"yiisoft/yii2-bootstrap","description":"The Twitter Bootstrap extension for the Yii framework","keywords":["bootstrap","yii2"],"homepage":"","version":"2.0.0","version_normalized":"2.0.0.0","license":["BSD-3-Clause"],"authors":[{"name":"Qiang Xue","email":"qiang.xue@gmail.com"}],"support":[],"dist":{"type":"zip","url":"https://api.github.com/repos/yiisoft/yii2-bootstrap/zipball/925395bd697c3ba2ce73937a7a236bdf26344417","reference":"925395bd697c3ba2ce73937a7a236bdf26344417","shasum":""},"type":"yii2-extension","time":"2014-10-12 17:09:06","autoload":{"psr-4":{"yii\\bootstrap\\":""}},"extra":{"branch-alias":{"dev-master":"2.0.x-dev"}},"require":{"yiisoft/yii2":"*","bower-asset/bootstrap":"3.2.* | 3.1.*"},"uid":865},"2.0.0-rc":{"name":"yiisoft/yii2-bootstrap","description":"The Twitter Bootstrap extension for the Yii framework","keywords":["bootstrap","yii2"],"homepage":"","version":"2.0.0-rc","version_normalized":"2.0.0.0-RC","license":["BSD-3-Clause"],"authors":[{"name":"Qiang Xue","email":"qiang.xue@gmail.com"}],"support":[],"dist":{"type":"zip","url":"https://api.github.com/repos/yiisoft/yii2-bootstrap/zipball/6db2c9b72384c23d18105056d569d1502d7cfab5","reference":"6db2c9b72384c23d18105056d569d1502d7cfab5","shasum":""},"type":"yii2-extension","time":"2014-09-28 01:59:54","autoload":{"psr-4":{"yii\\bootstrap\\":""}},"extra":{"branch-alias":{"dev-master":"2.0.x-dev"}},"require":{"yiisoft/yii2":"*","bower-asset/bootstrap":"3.2.* | 3.1.*"},"uid":866},"2.0.0-beta":{"name":"yiisoft/yii2-bootstrap","description":"The Twitter Bootstrap extension for the Yii framework","keywords":["bootstrap","yii2"],"homepage":"","version":"2.0.0-beta","version_normalized":"2.0.0.0-beta","license":["BSD-3-Clause"],"authors":[{"name":"Qiang Xue","email":"qiang.xue@gmail.com","homepage":"http://www.yiiframework.com/","role":"Founder and project lead"}],"support":[],"dist":{"type":"zip","url":"https://api.github.com/repos/yiisoft/yii2-bootstrap/zipball/d2518d1f6fb0b3e0e3aba50b9c35f56d580eb3c4","reference":"d2518d1f6fb0b3e0e3aba50b9c35f56d580eb3c4","shasum":""},"type":"yii2-extension","time":"2014-04-13 21:58:59","autoload":{"psr-4":{"yii\\bootstrap\\":""}},"require":{"yiisoft/yii2":"*","twbs/bootstrap":"3.0.*"},"uid":867},"2.0.0-alpha":{"name":"yiisoft/yii2-bootstrap","description":"The Twitter Bootstrap extension for the Yii framework","keywords":["bootstrap","yii"],"homepage":"","version":"2.0.0-alpha","version_normalized":"2.0.0.0-alpha","license":["BSD-3-Clause"],"authors":[{"name":"Qiang Xue","email":"qiang.xue@gmail.com","homepage":"http://www.yiiframework.com/","role":"Founder and project lead"}],"support":[],"dist":{"type":"zip","url":"https://api.github.com/repos/yiisoft/yii2-bootstrap/zipball/efef49b381c686b542a78a34e48c3d3b8f15ff98","reference":"efef49b381c686b542a78a34e48c3d3b8f15ff98","shasum":""},"type":"yii2-extension","time":"2013-11-25 14:33:59","autoload":{"psr-0":{"yii\\bootstrap\\":""}},"target-dir":"yii/bootstrap","require":{"yiisoft/yii2":"*","twbs/bootstrap":"3.0.*"},"uid":868}}}}