{"packages":{"pimple/pimple":{"v3.3.0":{"name":"pimple/pimple","description":"Pimple, a simple Dependency Injection Container","keywords":["dependency injection","container"],"homepage":"https://pimple.symfony.com","version":"v3.3.0","version_normalized":"3.3.0.0","license":["MIT"],"authors":[{"name":"Fabien Potencier","email":"fabien@symfony.com"}],"support":[],"dist":{"type":"zip","url":"https://api.github.com/repos/silexphp/Pimple/zipball/e55d12f9d6a0e7f9c85992b73df1267f46279930","reference":"e55d12f9d6a0e7f9c85992b73df1267f46279930","shasum":""},"type":"library","time":"2020-03-03 09:12:48","autoload":{"psr-0":{"Pimple":"src/"}},"extra":{"branch-alias":{"dev-master":"3.3.x-dev"}},"require":{"php":"^7.2.5","psr/container":"^1.0"},"uid":49847},"v1.0.2":{"name":"pimple/pimple","description":"Pimple is a simple Dependency Injection Container for PHP 5.3","keywords":["dependency injection","container"],"homepage":"http://pimple.sensiolabs.org","version":"v1.0.2","version_normalized":"1.0.2.0","license":["MIT"],"authors":[{"name":"Fabien Potencier","email":"fabien@symfony.com"}],"support":[],"dist":{"type":"zip","url":"https://api.github.com/repos/silexphp/Pimple/zipball/ae11e57e8c2bb414b2ff93396dbbfc0eb92feb94","reference":"ae11e57e8c2bb414b2ff93396dbbfc0eb92feb94","shasum":""},"type":"library","time":"2013-03-08 08:21:40","autoload":{"psr-0":{"Pimple":"lib/"}},"extra":{"branch-alias":{"dev-master":"1.0.x-dev"}},"require":{"php":">=5.3.0"},"uid":45318},"v3.2.3":{"name":"pimple/pimple","description":"Pimple, a simple Dependency Injection Container","keywords":["dependency injection","container"],"homepage":"http://pimple.sensiolabs.org","version":"v3.2.3","version_normalized":"3.2.3.0","license":["MIT"],"authors":[{"name":"Fabien Potencier","email":"fabien@symfony.com"}],"support":[],"dist":{"type":"zip","url":"https://api.github.com/repos/silexphp/Pimple/zipball/9e403941ef9d65d20cba7d54e29fe906db42cf32","reference":"9e403941ef9d65d20cba7d54e29fe906db42cf32","shasum":""},"type":"library","time":"2018-01-21 07:42:36","autoload":{"psr-0":{"Pimple":"src/"}},"extra":{"branch-alias":{"dev-master":"3.2.x-dev"}},"require":{"php":">=5.3.0","psr/container":"^1.0"},"uid":12764},"v3.2.2":{"name":"pimple/pimple","description":"Pimple, a simple Dependency Injection Container","keywords":["dependency injection","container"],"homepage":"http://pimple.sensiolabs.org","version":"v3.2.2","version_normalized":"3.2.2.0","license":["MIT"],"authors":[{"name":"Fabien Potencier","email":"fabien@symfony.com"}],"support":[],"dist":{"type":"zip","url":"https://api.github.com/repos/silexphp/Pimple/zipball/4d45fb62d96418396ec58ba76e6f065bca16e10a","reference":"4d45fb62d96418396ec58ba76e6f065bca16e10a","shasum":""},"type":"library","time":"2017-07-23 07:32:15","autoload":{"psr-0":{"Pimple":"src/"}},"extra":{"branch-alias":{"dev-master":"3.2.x-dev"}},"require":{"php":">=5.3.0","psr/container":"^1.0"},"uid":2204},"v3.2.1":{"name":"pimple/pimple","description":"Pimple, a simple Dependency Injection Container","keywords":["dependency injection","container"],"homepage":"http://pimple.sensiolabs.org","version":"v3.2.1","version_normalized":"3.2.1.0","license":["MIT"],"authors":[{"name":"Fabien Potencier","email":"fabien@symfony.com"}],"support":[],"dist":{"type":"zip","url":"https://api.github.com/repos/silexphp/Pimple/zipball/ea636ec4ff99cc8d1d18a32fe6a16ef910565f6c","reference":"ea636ec4ff99cc8d1d18a32fe6a16ef910565f6c","shasum":""},"type":"library","time":"2017-07-18 08:42:19","autoload":{"psr-0":{"Pimple":"src/"}},"extra":{"branch-alias":{"dev-master":"3.2.x-dev"}},"require":{"php":">=5.3.0","psr/container":"^1.0"},"uid":2205},"v3.2.0":{"name":"pimple/pimple","description":"Pimple, a simple Dependency Injection Container","keywords":["dependency injection","container"],"homepage":"http://pimple.sensiolabs.org","version":"v3.2.0","version_normalized":"3.2.0.0","license":["MIT"],"authors":[{"name":"Fabien Potencier","email":"fabien@symfony.com"}],"support":[],"dist":{"type":"zip","url":"https://api.github.com/repos/silexphp/Pimple/zipball/729436408ef52f9845f9b60d60b2563f314bf1a9","reference":"729436408ef52f9845f9b60d60b2563f314bf1a9","shasum":""},"type":"library","time":"2017-07-17 17:05:21","autoload":{"psr-0":{"Pimple":"src/"}},"extra":{"branch-alias":{"dev-master":"3.2.x-dev"}},"require":{"php":">=5.3.0","psr/container":"^1.0"},"uid":2206},"v3.1.0":{"name":"pimple/pimple","description":"Pimple, a simple Dependency Injection Container","keywords":["dependency injection","container"],"homepage":"http://pimple.sensiolabs.org","version":"v3.1.0","version_normalized":"3.1.0.0","license":["MIT"],"authors":[{"name":"Fabien Potencier","email":"fabien@symfony.com"}],"support":[],"dist":{"type":"zip","url":"https://api.github.com/repos/silexphp/Pimple/zipball/279b56046fb368deacf77e2f8f3bdcea45cc367a","reference":"279b56046fb368deacf77e2f8f3bdcea45cc367a","shasum":""},"type":"library","time":"2017-07-03 14:06:46","autoload":{"psr-0":{"Pimple":"src/"}},"extra":{"branch-alias":{"dev-master":"3.1.x-dev"}},"require":{"php":">=5.3.0","psr/container":"^1.0"},"uid":2207},"v3.0.2":{"name":"pimple/pimple","description":"Pimple, a simple Dependency Injection Container","keywords":["dependency injection","container"],"homepage":"http://pimple.sensiolabs.org","version":"v3.0.2","version_normalized":"3.0.2.0","license":["MIT"],"authors":[{"name":"Fabien Potencier","email":"fabien@symfony.com"}],"support":[],"dist":{"type":"zip","url":"https://api.github.com/repos/silexphp/Pimple/zipball/a30f7d6e57565a2e1a316e1baf2a483f788b258a","reference":"a30f7d6e57565a2e1a316e1baf2a483f788b258a","shasum":""},"type":"library","time":"2015-09-11 15:10:35","autoload":{"psr-0":{"Pimple":"src/"}},"extra":{"branch-alias":{"dev-master":"3.0.x-dev"}},"require":{"php":">=5.3.0"},"uid":2208},"v3.0.1":{"name":"pimple/pimple","description":"Pimple is a simple Dependency Injection Container for PHP 5.3","keywords":["dependency injection","container"],"homepage":"http://pimple.sensiolabs.org","version":"v3.0.1","version_normalized":"3.0.1.0","license":["MIT"],"authors":[{"name":"Fabien Potencier","email":"fabien@symfony.com"}],"support":[],"dist":{"type":"zip","url":"https://api.github.com/repos/silexphp/Pimple/zipball/3313af5935dbc560fab845b76a1ca351b47855af","reference":"3313af5935dbc560fab845b76a1ca351b47855af","shasum":""},"type":"library","time":"2015-07-30 09:57:46","autoload":{"psr-0":{"Pimple":"src/"}},"extra":{"branch-alias":{"dev-master":"3.0.x-dev"}},"require":{"php":">=5.3.0"},"uid":2209},"v3.0.0":{"name":"pimple/pimple","description":"Pimple is a simple Dependency Injection Container for PHP 5.3","keywords":["dependency injection","container"],"homepage":"http://pimple.sensiolabs.org","version":"v3.0.0","version_normalized":"3.0.0.0","license":["MIT"],"authors":[{"name":"Fabien Potencier","email":"fabien@symfony.com"}],"support":[],"dist":{"type":"zip","url":"https://api.github.com/repos/silexphp/Pimple/zipball/876bf0899d01feacd2a2e83f04641e51350099ef","reference":"876bf0899d01feacd2a2e83f04641e51350099ef","shasum":""},"type":"library","time":"2014-07-24 09:48:15","autoload":{"psr-0":{"Pimple":"src/"}},"extra":{"branch-alias":{"dev-master":"3.0.x-dev"}},"require":{"php":">=5.3.0"},"uid":2210}}}}